wikigen/__init__.py
wikigen/cli.py
wikigen/config.py
wikigen/defaults.py
wikigen/flows/__init__.py
wikigen/flows/flow.py
wikigen/formatter/help_formatter.py
wikigen/formatter/init_formatter.py
wikigen/formatter/output_formatter.py
wikigen/mcp/__init__.py
wikigen/mcp/chunking.py
wikigen/mcp/embeddings.py
wikigen/mcp/output_resources.py
wikigen/mcp/search_index.py
wikigen/mcp/server.py
wikigen/mcp/vector_index.py
wikigen/metadata/__init__.py
wikigen/metadata/logo.py
wikigen/metadata/project.py
wikigen/metadata/version.py
wikigen/nodes/__init__.py
wikigen/nodes/nodes.py
wikigen/utils/__init__.py
wikigen/utils/adjust_headings.py
wikigen/utils/call_llm.py
wikigen/utils/crawl_github_files.py
wikigen/utils/crawl_local_files.py
wikigen/utils/llm_providers.py
wikigen/utils/version_check.py
wikigen-1.0.0.dist-info/licenses/LICENSE
wikigen-1.0.0.dist-info/METADATA
wikigen-1.0.0.dist-info/WHEEL
wikigen-1.0.0.dist-info/entry_points.txt
wikigen-1.0.0.dist-info/top_level.txt
wikigen-1.0.0.dist-info/RECORD
