Metadata-Version: 2.4
Name: wikigen
Version: 1.0.0
Summary: Wiki's for nerds, by nerds
Author: Mithun Ramesh
License-Expression: MIT
Project-URL: Homepage, https://github.com/usesalt/wikigen
Project-URL: Repository, https://github.com/usesalt/wikigen
Project-URL: Issues, https://github.com/usesalt/wikigen/issues
Classifier: Development Status :: 3 - Alpha
Classifier: Intended Audience :: Developers
Classifier: Operating System :: OS Independent
Classifier: Programming Language :: Python :: 3
Classifier: Programming Language :: Python :: 3.12
Classifier: Programming Language :: Python :: 3.13
Classifier: Programming Language :: Python :: 3.14
Classifier: Topic :: Software Development :: Documentation
Classifier: Topic :: Text Processing :: Markup
Requires-Python: >=3.12
License-File: LICENSE
Requires-Dist: pocketflow>=0.0.1
Requires-Dist: pyyaml>=6.0
Requires-Dist: requests>=2.28.0
Requires-Dist: gitpython>=3.1.0
Requires-Dist: google-genai>=1.9.0
Requires-Dist: pathspec>=0.11.0
Requires-Dist: keyring>=24.0.0
Requires-Dist: mcp>=1.19.0
Requires-Dist: faiss-cpu>=1.7.4
Requires-Dist: sentence-transformers>=2.2.0
Requires-Dist: numpy>=1.24.0
Dynamic: license-file
Dynamic: requires-python
